<?xml version="1.0" encoding="UTF-8" standalone="no"?><CFG><Node><Name>2</Name><Line>77</Line></Node><Node><Name>3</Name><Line>79</Line></Node><Node><Name>4</Name><Line>80</Line></Node><Node><Name>5</Name><Line>84</Line></Node><Node><Name>6</Name><Line>85</Line></Node><Node><Name>7</Name><Line>89</Line></Node><Node><Name>8</Name><Line>90</Line></Node><Node><Name>9</Name><Line>94</Line></Node><Node><Name>10</Name><Line>95</Line></Node><Node><Name>11</Name><Line>99</Line></Node><Node><Name>12</Name><Line>100</Line></Node><Node><Name>13</Name><Line>104</Line></Node><Node><Name>14</Name><Line>105</Line></Node><Node><Name>15</Name><Line>109</Line></Node><Node><Name>16</Name><Line>110</Line></Node><Node><Name>17</Name><Line>113</Line></Node><Node><Name>18</Name><Line>START</Line></Node><Node><Name>19</Name><Line>EXIT</Line></Node><Edge><Source>18</Source><Target>2</Target><Boolean/><ID><Val>6@345</Val><Val>10@348</Val><Val>12@350</Val><Val>21@345</Val><Val>24@343</Val><Val>25@361</Val><Val>35@331</Val><Val>42@357</Val><Val>43@344</Val><Val>52@344</Val><Val>61@330</Val><Val>64@329</Val><Val>71@331</Val><Val>73@350</Val><Val>74@364</Val><Val>75@351</Val><Val>82@342</Val><Val>83@358</Val><Val>98@347</Val><Val>105@352</Val><Val>111@345</Val><Val>112@351</Val><Val>117@345</Val><Val>120@335</Val></ID></Edge><Edge><Source>2</Source><Target>3</Target><Boolean/><ID><Val>6@346</Val><Val>10@349</Val><Val>12@351</Val><Val>21@346</Val><Val>24@344</Val><Val>25@362</Val><Val>35@332</Val><Val>42@358</Val><Val>43@345</Val><Val>52@345</Val><Val>61@331</Val><Val>64@330</Val><Val>71@332</Val><Val>73@351</Val><Val>74@365</Val><Val>75@352</Val><Val>82@343</Val><Val>83@359</Val><Val>98@348</Val><Val>105@353</Val><Val>111@346</Val><Val>112@352</Val><Val>117@346</Val><Val>120@336</Val></ID></Edge><Edge><Source>3</Source><Target>4</Target><Boolean>true</Boolean><ID><Val>52@346</Val><Val>82@344</Val><Val>98@349</Val><Val>111@347</Val><Val>117@347</Val></ID></Edge><Edge><Source>3</Source><Target>5</Target><Boolean>false</Boolean><ID><Val>6@347</Val><Val>10@350</Val><Val>12@352</Val><Val>21@347</Val><Val>24@345</Val><Val>25@363</Val><Val>35@333</Val><Val>42@359</Val><Val>43@346</Val><Val>61@332</Val><Val>64@331</Val><Val>71@333</Val><Val>73@352</Val><Val>74@366</Val><Val>75@353</Val><Val>83@360</Val><Val>105@354</Val><Val>112@353</Val><Val>120@337</Val></ID></Edge><Edge><Source>5</Source><Target>6</Target><Boolean>true</Boolean><ID><Val>6@348</Val></ID></Edge><Edge><Source>5</Source><Target>7</Target><Boolean>false</Boolean><ID><Val>10@351</Val><Val>12@353</Val><Val>21@348</Val><Val>24@346</Val><Val>25@364</Val><Val>35@334</Val><Val>42@360</Val><Val>43@347</Val><Val>61@333</Val><Val>64@332</Val><Val>71@334</Val><Val>73@353</Val><Val>74@367</Val><Val>75@354</Val><Val>83@361</Val><Val>105@355</Val><Val>112@354</Val><Val>120@338</Val></ID></Edge><Edge><Source>7</Source><Target>8</Target><Boolean>true</Boolean><ID><Val>24@347</Val></ID></Edge><Edge><Source>7</Source><Target>9</Target><Boolean>false</Boolean><ID><Val>10@352</Val><Val>12@354</Val><Val>21@349</Val><Val>25@365</Val><Val>35@335</Val><Val>42@361</Val><Val>43@348</Val><Val>61@334</Val><Val>64@333</Val><Val>71@335</Val><Val>73@354</Val><Val>74@368</Val><Val>75@355</Val><Val>83@362</Val><Val>105@356</Val><Val>112@355</Val><Val>120@339</Val></ID></Edge><Edge><Source>9</Source><Target>10</Target><Boolean>true</Boolean><ID><Val>83@363</Val></ID></Edge><Edge><Source>9</Source><Target>11</Target><Boolean>false</Boolean><ID><Val>10@353</Val><Val>12@355</Val><Val>21@350</Val><Val>25@366</Val><Val>35@336</Val><Val>42@362</Val><Val>43@349</Val><Val>61@335</Val><Val>64@334</Val><Val>71@336</Val><Val>73@355</Val><Val>74@369</Val><Val>75@356</Val><Val>105@357</Val><Val>112@356</Val><Val>120@340</Val></ID></Edge><Edge><Source>11</Source><Target>12</Target><Boolean>true</Boolean><ID><Val>10@354</Val><Val>25@367</Val><Val>42@363</Val><Val>73@356</Val><Val>75@357</Val><Val>105@358</Val></ID></Edge><Edge><Source>11</Source><Target>13</Target><Boolean>false</Boolean><ID><Val>12@356</Val><Val>21@351</Val><Val>35@337</Val><Val>43@350</Val><Val>61@336</Val><Val>64@335</Val><Val>71@337</Val><Val>74@370</Val><Val>112@357</Val><Val>120@341</Val></ID></Edge><Edge><Source>13</Source><Target>14</Target><Boolean>true</Boolean><ID><Val>43@351</Val><Val>74@371</Val><Val>112@358</Val></ID></Edge><Edge><Source>13</Source><Target>15</Target><Boolean>false</Boolean><ID><Val>12@357</Val><Val>21@352</Val><Val>35@338</Val><Val>61@337</Val><Val>64@336</Val><Val>71@338</Val><Val>120@342</Val></ID></Edge><Edge><Source>15</Source><Target>16</Target><Boolean>true</Boolean><ID><Val>12@358</Val><Val>21@353</Val><Val>35@339</Val><Val>61@338</Val><Val>64@337</Val><Val>71@339</Val><Val>120@343</Val></ID></Edge><Edge><Source>15</Source><Target>17</Target><Boolean>false</Boolean><ID/></Edge><Edge><Source>4</Source><Target>19</Target><Boolean/><ID><Val>52@347</Val><Val>82@345</Val><Val>98@350</Val><Val>111@348</Val><Val>117@348</Val></ID></Edge><Edge><Source>6</Source><Target>19</Target><Boolean/><ID><Val>6@349</Val></ID></Edge><Edge><Source>8</Source><Target>19</Target><Boolean/><ID><Val>24@348</Val></ID></Edge><Edge><Source>10</Source><Target>19</Target><Boolean/><ID><Val>83@364</Val></ID></Edge><Edge><Source>12</Source><Target>19</Target><Boolean/><ID><Val>10@355</Val><Val>25@368</Val><Val>42@364</Val><Val>73@357</Val><Val>75@358</Val><Val>105@359</Val></ID></Edge><Edge><Source>14</Source><Target>19</Target><Boolean/><ID><Val>43@352</Val><Val>74@372</Val><Val>112@359</Val></ID></Edge><Edge><Source>16</Source><Target>19</Target><Boolean/><ID><Val>12@359</Val><Val>21@354</Val><Val>35@340</Val><Val>61@339</Val><Val>64@338</Val><Val>71@340</Val><Val>120@344</Val></ID></Edge><Edge><Source>17</Source><Target>19</Target><Boolean/><ID/></Edge><Origin><Val>TemplateFactory.getTemplate:6@344</Val><Val>TemplateFactory.getTemplate:10@347</Val><Val>TemplateFactory.getTemplate:12@349</Val><Val>TemplateFactory.getTemplate:21@344</Val><Val>TemplateFactory.getTemplate:24@342</Val><Val>TemplateFactory.getTemplate:25@360</Val><Val>TemplateFactory.getTemplate:35@330</Val><Val>TemplateFactory.getTemplate:42@356</Val><Val>TemplateFactory.getTemplate:43@343</Val><Val>TemplateFactory.getTemplate:52@343</Val><Val>TemplateFactory.getTemplate:61@329</Val><Val>TemplateFactory.getTemplate:64@328</Val><Val>TemplateFactory.getTemplate:71@330</Val><Val>TemplateFactory.getTemplate:73@349</Val><Val>TemplateFactory.getTemplate:74@363</Val><Val>TemplateFactory.getTemplate:75@350</Val><Val>TemplateFactory.getTemplate:82@341</Val><Val>TemplateFactory.getTemplate:83@357</Val><Val>TemplateFactory.getTemplate:98@346</Val><Val>TemplateFactory.getTemplate:105@351</Val><Val>TemplateFactory.getTemplate:111@344</Val><Val>TemplateFactory.getTemplate:112@350</Val><Val>TemplateFactory.getTemplate:117@344</Val><Val>TemplateFactory.getTemplate:120@334</Val></Origin></CFG>